typelets/__init__.py
typelets/_version.py
typelets/funcs.py
typelets/json.py
typelets/py.typed
typelets/runtime.py
typelets/symbols.py
typelets/django/__init__.py
typelets/django/auth.py
typelets/django/forms.py
typelets/django/json.py
typelets/django/models.py
typelets/django/strings.py
typelets/django/urls.py
typelets/tests/__init__.py
typelets/tests/test_funcs.py
typelets-1.1.dist-info/licenses/LICENSE
typelets-1.1.dist-info/METADATA
typelets-1.1.dist-info/WHEEL
typelets-1.1.dist-info/top_level.txt
typelets-1.1.dist-info/RECORD
