Metadata-Version: 2.4
Name: typelets
Version: 1.1
Summary: Type hints and utility objects for Python and Django projects.
Author-email: "Beanbag, Inc." <questions@beanbaginc.com>
License: MIT
Project-URL: homepage, https://typelets.readthedocs.io/
Project-URL: documentation, https://typelets.readthedocs.io/
Project-URL: repository, https://github.com/beanbaginc/python-typelets
Classifier: Development Status :: 5 - Production/Stable
Classifier: Environment :: Other Environment
Classifier: Intended Audience :: Developers
Classifier: License :: OSI Approved :: MIT License
Classifier: Operating System :: OS Independent
Classifier: Programming Language :: Python
Classifier: Programming Language :: Python :: 3
Classifier: Programming Language :: Python :: 3.8
Classifier: Programming Language :: Python :: 3.9
Classifier: Programming Language :: Python :: 3.10
Classifier: Programming Language :: Python :: 3.11
Classifier: Programming Language :: Python :: 3.12
Classifier: Programming Language :: Python :: 3.13
Classifier: Topic :: Software Development
Classifier: Topic :: Software Development :: Libraries
Classifier: Topic :: Software Development :: Libraries :: Python Modules
Requires-Python: >=3.8
License-File: LICENSE
Requires-Dist: typing_extensions>=4.4
Dynamic: license-file
